pyfwg/__init__.py
pyfwg/api.py
pyfwg/constants.py
pyfwg/iterator.py
pyfwg/utils.py
pyfwg/workflow.py
pyfwg/tutorials/epw_morph_global_europe_example.ipynb
pyfwg/tutorials/morphingiterator_example.ipynb
pyfwg/tutorials/morphingworkflow_global_europe_example.ipynb
pyfwg/tutorials/my_parametric_study.xlsx
pyfwg/tutorials/my_parametric_study_modified.xlsx
pyfwg/tutorials/epws/w_pattern/london_uhi-type-2.epw
pyfwg/tutorials/epws/w_pattern/sevilla_uhi-type-1.epw
pyfwg/tutorials/epws/wo_pattern/GBR_London.Gatwick.037760_IWEC_uhi_type-2.epw
pyfwg/tutorials/epws/wo_pattern/sevilla_in_this_one_the_uhi_is_type-1.epw
pyfwg-0.3.0.dist-info/licenses/LICENSE
pyfwg-0.3.0.dist-info/METADATA
pyfwg-0.3.0.dist-info/WHEEL
pyfwg-0.3.0.dist-info/top_level.txt
pyfwg-0.3.0.dist-info/RECORD
