Metadata-Version: 2.4
Name: pyfwg
Version: 0.3.0
Summary: A Python workflow manager for the Future Weather Generator tool.
Home-page: https://github.com/dsanchez-garcia/pyfwg
Author: Daniel Sánchez-García
Author-email: daniel.sanchezgarcia@uca.es
License: MIT
Project-URL: Bug Tracker, https://github.com/dsanchez-garcia/pyfwg/issues
Project-URL: Documentation, https://pyfwg.readthedocs.io/
Classifier: Development Status :: 4 - Beta
Classifier: Intended Audience :: Science/Research
Classifier: Operating System :: OS Independent
Classifier: Programming Language :: Python :: 3
Classifier: Programming Language :: Python :: 3.8
Classifier: Programming Language :: Python :: 3.9
Classifier: Programming Language :: Python :: 3.10
Classifier: Programming Language :: Python :: 3.11
Classifier: Topic :: Scientific/Engineering
Requires-Python: >=3.9
License-File: LICENSE
Requires-Dist: importlib_resources; python_version < "3.9"
Requires-Dist: pandas
Requires-Dist: colorlog
Provides-Extra: docs
Requires-Dist: sphinx; extra == "docs"
Requires-Dist: sphinx-rtd-theme; extra == "docs"
Requires-Dist: nbsphinx; extra == "docs"
Dynamic: author
Dynamic: author-email
Dynamic: classifier
Dynamic: description
Dynamic: description-content-type
Dynamic: home-page
Dynamic: license
Dynamic: license-file
Dynamic: project-url
Dynamic: provides-extra
Dynamic: requires-dist
Dynamic: requires-python
Dynamic: summary
